yoto_exception/__info__.py
yoto_exception/__init__.py
yoto_exception/auth.py
yoto_exception/connection.py
yoto_exception/custom_exc.py
yoto_exception/forbidden.py
yoto_exception/maximum.py
yoto_exception/permission.py
yoto_exception/rpc.py
yoto_exception/unknown.py
yoto_exception-0.1.1.data/data/LICENSE.md
yoto_exception-0.1.1.dist-info/LICENSE.md
yoto_exception-0.1.1.dist-info/METADATA
yoto_exception-0.1.1.dist-info/WHEEL
yoto_exception-0.1.1.dist-info/top_level.txt
yoto_exception-0.1.1.dist-info/RECORD
