Metadata-Version: 2.1
Name: yoto-exception
Version: 0.1.1
Summary: yoto_api的异常模块
Home-page: https://gitlab.corp.funji.club/funji_dev/im/yoto_exception.git
Author: 有大家科技有限公司
Author-email: dev@funji.club
License: BSD
Platform: UNKNOWN
Classifier: Development Status :: 4 - Beta
Classifier: Environment :: Web Environment
Classifier: Intended Audience :: Developers
Classifier: License :: OSI Approved :: BSD License
Classifier: Operating System :: OS Independent
Classifier: Programming Language :: Python :: 3.9
Requires-Python: >=3.9
